napari_h5/__init__.py
napari_h5/_reader.py
napari_h5/_writer.py
napari_h5/napari.yaml
napari_h5/_tests/__init__.py
napari_h5/_tests/test_reader.py
napari_h5/_tests/test_writer.py
napari_h5-0.0.8.dist-info/LICENSE
napari_h5-0.0.8.dist-info/METADATA
napari_h5-0.0.8.dist-info/WHEEL
napari_h5-0.0.8.dist-info/entry_points.txt
napari_h5-0.0.8.dist-info/top_level.txt
napari_h5-0.0.8.dist-info/RECORD
