Metadata-Version: 2.1
Name: napari-h5
Version: 0.0.8
Summary: A hdf5 file reader plugin for napari
Home-page: https://github.com/rosalindfranklininstitute/napari-h5
Author: Luis Perdigao
Author-email: luis.perdigao@rfi.ac.uk
License: Apache-2.0
Project-URL: Bug Tracker, https://github.com/rosalindfranklininstitute/napari-h5/issues
Project-URL: Documentation, https://github.com/rosalindfranklininstitute/napari-h5#readme
Project-URL: Source Code, https://github.com/rosalindfranklininstitute/napari-h5
Project-URL: User Support, https://github.com/rosalindfranklininstitute/napari-h5/issues
Classifier: Development Status :: 2 - Pre-Alpha
Classifier: Framework :: napari
Classifier: Intended Audience :: Developers
Classifier: License :: OSI Approved :: Apache Software License
Classifier: Operating System :: OS Independent
Classifier: Programming Language :: Python
Classifier: Programming Language :: Python :: 3
Classifier: Programming Language :: Python :: 3 :: Only
Classifier: Programming Language :: Python :: 3.8
Classifier: Programming Language :: Python :: 3.9
Classifier: Programming Language :: Python :: 3.10
Classifier: Topic :: Scientific/Engineering :: Image Processing
Requires-Python: >=3.8
License-File: LICENSE
Requires-Dist: numpy
Requires-Dist: h5py
Provides-Extra: testing
Requires-Dist: tox ; extra == 'testing'
Requires-Dist: pytest ; extra == 'testing'
Requires-Dist: pytest-cov ; extra == 'testing'
